b2bapi/__init__.py
b2bapi/madlib.py
b2bapi/meme.py
b2bapi/text.py
b2bapi/word.py
b2bapi/wrapper.py
b2bapi-2.1.2.dist-info/LICENSE
b2bapi-2.1.2.dist-info/METADATA
b2bapi-2.1.2.dist-info/WHEEL
b2bapi-2.1.2.dist-info/top_level.txt
b2bapi-2.1.2.dist-info/RECORD
