Metadata-Version: 2.1
Name: b2bapi
Version: 2.1.2
Summary: Interact with the BytesToBits API through Python
Home-page: https://github.com/doublevcodes/b2bapi
License: UNKNOWN
Platform: UNKNOWN
Requires-Dist: aiohttp
